[
    {
        "timestamp": 1724572500000,
        "open": 2742.81,
        "high": 2743.81,
        "low": 2741.88,
        "close": 2743.81,
        "volume": 3.99211482
    },
    {
        "timestamp": 1724572800000,
        "open": 2744.05,
        "high": 2744.45,
        "low": 2740.65,
        "close": 2740.65,
        "volume": 0.53797215
    },
    {
        "timestamp": 1724573100000,
        "open": 2740.66,
        "high": 2748.47,
        "low": 2740.66,
        "close": 2748.45,
        "volume": 18.8558531
    },
    {
        "timestamp": 1724573400000,
        "open": 2748.46,
        "high": 2748.47,
        "low": 2746.35,
        "close": 2747.31,
        "volume": 3.86943735
    },
    {
        "timestamp": 1724573700000,
        "open": 2747.54,
        "high": 2748.47,
        "low": 2747.53,
        "close": 2748.46,
        "volume": 2.84596278
    }
]